anysync/__init__.py
anysync/_private.py
anysync/core.py
anysync/py.typed
anysync-1.0.2.dist-info/METADATA
anysync-1.0.2.dist-info/WHEEL
anysync-1.0.2.dist-info/licenses/LICENSE.txt
anysync-1.0.2.dist-info/RECORD
