Metadata-Version: 2.4
Name: anysync
Version: 1.0.2
Summary: A lightweight library for allowing async functions to be called in a synchronous manner.
Project-URL: Source, https://github.com/rmorshea/anysync
Author-email: Ryan Morshead <ryan.morshead@gmail.com>
License: MIT License
License-File: LICENSE.txt
Classifier: Development Status :: 4 - Beta
Classifier: Programming Language :: Python
Requires-Python: <4,>=3.10
Requires-Dist: anyio<5,>=4
Requires-Dist: sniffio<2,>=1
Requires-Dist: typing-extensions<5,>=4
